celcat_scraper/__init__.py
celcat_scraper/api.py
celcat_scraper/auth.py
celcat_scraper/config.py
celcat_scraper/exceptions.py
celcat_scraper/filter.py
celcat_scraper/scraper.py
celcat_scraper/types.py
celcat_scraper/utils.py
celcat_scraper-1.1.3.dist-info/METADATA
celcat_scraper-1.1.3.dist-info/WHEEL
celcat_scraper-1.1.3.dist-info/licenses/LICENSE
celcat_scraper-1.1.3.dist-info/RECORD
