Metadata-Version: 2.4
Name: celcat_scraper
Version: 1.1.3
Summary: Asynchronous Python scraper for Celcat Calendar
Project-URL: Homepage, https://github.com/etiennec78/celcat-scraper
Project-URL: Issues, https://github.com/etiennec78/celcat-scraper/issues
Author-email: Etienne Coriou <etienne.coriou@free.fr>
License-File: LICENSE
Classifier: Framework :: AsyncIO
Classifier: Intended Audience :: Developers
Classifier: License :: OSI Approved :: MIT License
Classifier: Operating System :: OS Independent
Classifier: Programming Language :: Python :: 3
Requires-Python: >=3.8
Requires-Dist: aiohttp>=3.8.0
Requires-Dist: beautifulsoup4>=4.4.0
